{
  "duas": [
    {
      "number": "1",
      "arabicText": "سُبْحَانَ الْمَلِكِ الْقُدُوس ﴿۱﴾ رَبُّ الْمَلَائِكَةِ وَالرُّوحِِ ﴿۲﴾",
      "readText": "subhaanal-malikil-qudduusi.1robbil-malaa'ikati warruuhi.2",
      "indoText": "“Maha suci (Engkau Ya Allah), Raja Yang Maha suci, Tuhan-nya para malaikat dan malaikat Jibril “ \nDibaca tiga kali dan yang ketiganya dikeraskan serta dipanjangkan suaranya dengan berkata: \nرَبِّ الْمَلاَئِكَةِ وَالرُّوْحِ \n“Tuhan-nya para malaikat dan malaikat Jibril“.",
      "refs": "Referensi :\nAn-Nasa'i 3/244, Ad-Daraqutni."
    }
  ]
}